reach/__init__.py
reach/append.py
reach/query_data.py
reach/rate_limiter.py
reach/reach.py
tests/__init__.py
tests/base.py
tests/responses.py
tests/test_append.py
tests/test_reach_client.py
tests/utils.py
versium_reach_sdk-1.1.0.dist-info/LICENSE
versium_reach_sdk-1.1.0.dist-info/METADATA
versium_reach_sdk-1.1.0.dist-info/WHEEL
versium_reach_sdk-1.1.0.dist-info/top_level.txt
versium_reach_sdk-1.1.0.dist-info/RECORD
