Metadata-Version: 2.1
Name: versium-reach-sdk
Version: 1.1.0
Summary: Python SDK for querying Versium Reach APIs
Home-page: https://github.com/VersiumAnalytics/reach-api-python-sdk
Author: Versium Analytics, Inc.
Author-email: "Versium Analytics, Inc." <opensource@versium.com>
License: Copyright 2022 Versium Analytics, Inc.
Project-URL: Homepage, https://api-documentation.versium.com/
Project-URL: Documentation, https://api-documentation.versium.com/reference/welcome
Project-URL: Repository, https://github.com/VersiumAnalytics/reach-api-python-sdk
Project-URL: API Trial Account, https://app.versium.com/create-developer-account
Keywords: Versium,MarTech,API,SDK,Data Enrichment,Data Appends,Marketing,B2B,B2C,Audience,Identity Graph
Classifier: Programming Language :: Python :: 3
Classifier: License :: OSI Approved :: BSD License
Classifier: Operating System :: OS Independent
Requires-Python: ~=3.7
License-File: LICENSE
Requires-Dist: aiohttp (>=3.8.0)
